upstream_analyzer/__init__.py
upstream_analyzer/analyze_basin.py
upstream_analyzer-0.1.4.dist-info/METADATA
upstream_analyzer-0.1.4.dist-info/WHEEL
upstream_analyzer-0.1.4.dist-info/top_level.txt
upstream_analyzer-0.1.4.dist-info/RECORD
