Metadata-Version: 2.1
Name: upstream_analyzer
Version: 0.1.4
Summary: A Python package for analyzing upstream basins and resampling DEM data
Home-page: https://github.com/jlonghku/UpstreamAnalyzer
Author: Long Jiang
Author-email: jlong@connect.hku.hk
Classifier: Programming Language :: Python :: 3
Classifier: License :: OSI Approved :: MIT License
Classifier: Operating System :: OS Independent
Requires-Python: >=3.6
Requires-Dist: numpy
Requires-Dist: pysheds
Requires-Dist: matplotlib
Requires-Dist: scipy
Requires-Dist: pyproj
